auth_manager/__init__.py
auth_manager/auth_manager.py
auth_manager-1.0.0.dist-info/LICENSE
auth_manager-1.0.0.dist-info/METADATA
auth_manager-1.0.0.dist-info/WHEEL
auth_manager-1.0.0.dist-info/top_level.txt
auth_manager-1.0.0.dist-info/RECORD
