Metadata-Version: 2.1
Name: auth-manager
Version: 1.0.0
License-File: LICENSE
Requires-Dist: boto3
